getport
