Metadata-Version: 1.0
Name: getport
Version: 0.1.2
Summary: get available port on your computer
Home-page: https://github.com/whatArePeopleDownloading/getport
Author: meta Z
Author-email: zycode277@gmail.com
License: MIT
Platform: UNKNOWN
